{
  "routes": [
    {
      "method": "GET",
      "path": "/contatoes",
      "handler": "contato.find",
      "config": {
        "policies": []
      }
    },
    {
      "method": "GET",
      "path": "/contatoes/count",
      "handler": "contato.count",
      "config": {
        "policies": []
      }
    },
    {
      "method": "GET",
      "path": "/contatoes/:id",
      "handler": "contato.findOne",
      "config": {
        "policies": []
      }
    },
    {
      "method": "POST",
      "path": "/contatoes",
      "handler": "contato.create",
      "config": {
        "policies": []
      }
    },
    {
      "method": "PUT",
      "path": "/contatoes/:id",
      "handler": "contato.update",
      "config": {
        "policies": []
      }
    },
    {
      "method": "DELETE",
      "path": "/contatoes/:id",
      "handler": "contato.delete",
      "config": {
        "policies": []
      }
    }
  ]
}
